plumeurl/__init__.py
plumeurl/main.py
plumeurl-1.0.1.dist-info/LICENSE
plumeurl-1.0.1.dist-info/METADATA
plumeurl-1.0.1.dist-info/WHEEL
plumeurl-1.0.1.dist-info/RECORD
