Metadata-Version: 2.3
Name: PlumeURL
Version: 1.0.1
Summary: Unofficial Plume URL API
License: MIT
Author: Awakno
Author-email: contact@awakno.fr
Requires-Python: >=3.8.1,<4.0.0
Classifier: License :: OSI Approved :: MIT License
Classifier: Programming Language :: Python :: 3
Classifier: Programming Language :: Python :: 3.9
Classifier: Programming Language :: Python :: 3.10
Classifier: Programming Language :: Python :: 3.11
Classifier: Programming Language :: Python :: 3.12
Classifier: Programming Language :: Python :: 3.13
Requires-Dist: aiohttp (>=3.9.5,<4.0.0)
Project-URL: Homepage, https://url.ptarmigan.xyz/
Project-URL: Repository, https://github.com/Awakno/plume-url.py
